astrosampler/__init__.py
astrosampler/imf.py
astrosampler/sampler.py
astrosampler-0.2.0.dist-info/METADATA
astrosampler-0.2.0.dist-info/WHEEL
astrosampler-0.2.0.dist-info/licenses/LICENSE
astrosampler-0.2.0.dist-info/RECORD
