Metadata-Version: 2.3
Name: astrosampler
Version: 0.2.0
Summary: A package for sampling typical distributions in astronomy
Project-URL: Homepage, https://github.com/Sub6Resources/astro-sampler
Project-URL: Issues, https://github.com/Sub6Resources/astro-sampler/issues
Author-email: Matthew Whitaker <sub6resources@gmail.com>
License-File: LICENSE
Classifier: Operating System :: OS Independent
Classifier: Programming Language :: Python :: 3
Classifier: Topic :: Scientific/Engineering
Requires-Python: >=3.10
Requires-Dist: numpy
